llama_index/utils/qianfan/__init__.py
llama_index/utils/qianfan/apis.py
llama_index/utils/qianfan/authorization.py
llama_index/utils/qianfan/client.py
llama_index_utils_qianfan-0.4.1.dist-info/METADATA
llama_index_utils_qianfan-0.4.1.dist-info/WHEEL
llama_index_utils_qianfan-0.4.1.dist-info/licenses/LICENSE
llama_index_utils_qianfan-0.4.1.dist-info/RECORD
