Metadata-Version: 2.4
Name: llama-index-utils-qianfan
Version: 0.4.1
Summary: llama-index utils baidu qianfan integration
Author-email: wencan <wencan@live.cn>
License-Expression: MIT
License-File: LICENSE
Requires-Python: <4.0,>=3.9
Requires-Dist: httpx<0.28,>=0.27.0
Requires-Dist: llama-index-core<0.15,>=0.13.0
